{
    "grandfather1": {
        "father1": {
            "son": {
                "grandchild": {
                    "name": "tom",
                    "age": 18,
                    "smart": 1,
                    "have_girlfriend": 0,
                    "class": "Grandchild"
                },
                "name": "Jim",
                "age": 40,
                "haveBoy": 1,
                "wife": "mei",
                "class": "Son"
            },
            "name": "Dave",
            "wife": "yun",
            "have_son": 1,
            "house": [
                "house",
                "house1",
                "house2"
            ],
            "field": "value",
            "class": "Father"
        },
        "father2": {
            "son": {
                "grandchild": {
                    "name": "tom",
                    "age": 18,
                    "smart": 1,
                    "have_girlfriend": 0
                },
                "name": "Jim",
                "age": 40,
                "haveBoy": 1,
                "wife": "mei"
            },
            "name": "Dave",
            "wife": "yun",
            "have_son": 1,
            "house": [
                "house",
                "house1",
                "house2"
            ]
        },
        "name": "ton",
        "retired": 1,
        "class": "Grandfather"
    },
    "grandfather2": {
        "father1": {
            "son": {
                "grandchild": {
                    "name": "tom",
                    "age": 18,
                    "smart": 1,
                    "have_girlfriend": 0
                },
                "name": "Jim",
                "age": 40,
                "haveBoy": 1,
                "wife": "mei"
            },
            "name": "Dave",
            "wife": "yun",
            "have_son": 1,
            "house": [
                "house",
                "house1",
                "house2"
            ]
        },
        "father2": {
            "son": {
                "grandchild": {
                    "name": "tom",
                    "age": 18,
                    "smart": 1,
                    "have_girlfriend": 0
                },
                "name": "Jim",
                "age": 40,
                "haveBoy": 1,
                "wife": "mei"
            },
            "name": "Dave",
            "wife": "yun",
            "have_son": 1,
            "house": [
                "house",
                "house1",
                "house2"
            ]
        },
        "name": "ton",
        "retired": 1
    }
}